vk_api-stubs/__init__.pyi
vk_api-stubs/audio.pyi
vk_api-stubs/audio_url_decoder.pyi
vk_api-stubs/bot_longpoll.pyi
vk_api-stubs/enums.pyi
vk_api-stubs/exceptions.pyi
vk_api-stubs/execute.pyi
vk_api-stubs/keyboard.pyi
vk_api-stubs/longpoll.pyi
vk_api-stubs/requests_pool.pyi
vk_api-stubs/streaming.pyi
vk_api-stubs/tools.pyi
vk_api-stubs/upload.pyi
vk_api-stubs/utils.pyi
vk_api-stubs/vk_api.pyi
vk_api_stubs-1.0.0.dist-info/WHEEL
vk_api_stubs-1.0.0.dist-info/METADATA
vk_api_stubs-1.0.0.dist-info/RECORD
